aff/__init__.py
aff-0.0.1.dist-info/LICENSE
aff-0.0.1.dist-info/METADATA
aff-0.0.1.dist-info/WHEEL
aff-0.0.1.dist-info/top_level.txt
aff-0.0.1.dist-info/RECORD
